{
  "generated": "2026-07-24T03:20:12.594Z",
  "period": {
    "start": "2026-07-17",
    "end": "2026-07-24"
  },
  "totalPageviews": 1296,
  "topGlossary": [
    {
      "path": "/glossary/spanking/",
      "views": 56
    },
    {
      "path": "/glossary/ddlg/",
      "views": 37
    },
    {
      "path": "/glossary/relationship-ds/",
      "views": 37
    },
    {
      "path": "/glossary/dominance-submission/",
      "views": 22
    },
    {
      "path": "/glossary/cuckold/",
      "views": 22
    }
  ],
  "topContent": [
    {
      "path": "/books/xiaolin-shengwu-shengfu-benshi/",
      "views": 9
    }
  ],
  "topOther": [
    {
      "path": "/",
      "views": 105
    },
    {
      "path": "/glossary/",
      "views": 64
    },
    {
      "path": "/books/",
      "views": 56
    },
    {
      "path": "/bibliography/",
      "views": 52
    },
    {
      "path": "/resources/",
      "views": 35
    }
  ],
  "countries": [
    {
      "code": "TW",
      "views": 455
    },
    {
      "code": "SG",
      "views": 338
    },
    {
      "code": "CN",
      "views": 134
    },
    {
      "code": "HK",
      "views": 109
    },
    {
      "code": "US",
      "views": 96
    },
    {
      "code": "JP",
      "views": 60
    },
    {
      "code": "CA",
      "views": 26
    },
    {
      "code": "DE",
      "views": 12
    },
    {
      "code": "VN",
      "views": 8
    },
    {
      "code": "GB",
      "views": 5
    }
  ],
  "lifetime": {
    "period": {
      "start": "2026-05-03",
      "end": "2026-07-24"
    },
    "totalPageviews": 18790,
    "countries": [
      {
        "code": "TW",
        "views": 7380
      },
      {
        "code": "SG",
        "views": 2680
      },
      {
        "code": "HK",
        "views": 2460
      },
      {
        "code": "US",
        "views": 1910
      },
      {
        "code": "CN",
        "views": 1310
      },
      {
        "code": "JP",
        "views": 1200
      },
      {
        "code": "KR",
        "views": 250
      },
      {
        "code": "CA",
        "views": 210
      },
      {
        "code": "MY",
        "views": 190
      },
      {
        "code": "VN",
        "views": 170
      }
    ]
  }
}