{
  "generated": "2026-07-12T03:31:10.545Z",
  "period": {
    "start": "2026-07-05",
    "end": "2026-07-12"
  },
  "totalPageviews": 1194,
  "topGlossary": [
    {
      "path": "/glossary/spanking/",
      "views": 46
    },
    {
      "path": "/glossary/relationship-ds/",
      "views": 44
    },
    {
      "path": "/glossary/bdsm/",
      "views": 28
    },
    {
      "path": "/glossary/slave-contract/",
      "views": 24
    },
    {
      "path": "/glossary/shibari/",
      "views": 22
    }
  ],
  "topContent": [
    {
      "path": "/books/xiaolin-shengwu-shengfu-benshi/",
      "views": 10
    },
    {
      "path": "/bibliography/ambler-2017/",
      "views": 10
    },
    {
      "path": "/books/sm-101/",
      "views": 9
    }
  ],
  "topOther": [
    {
      "path": "/",
      "views": 88
    },
    {
      "path": "/glossary/",
      "views": 63
    },
    {
      "path": "/resources/",
      "views": 41
    },
    {
      "path": "/books/",
      "views": 37
    },
    {
      "path": "/bibliography/",
      "views": 30
    }
  ],
  "countries": [
    {
      "code": "TW",
      "views": 361
    },
    {
      "code": "SG",
      "views": 328
    },
    {
      "code": "HK",
      "views": 195
    },
    {
      "code": "US",
      "views": 78
    },
    {
      "code": "CN",
      "views": 71
    },
    {
      "code": "JP",
      "views": 59
    },
    {
      "code": "VN",
      "views": 21
    },
    {
      "code": "MO",
      "views": 18
    },
    {
      "code": "AU",
      "views": 11
    },
    {
      "code": "PL",
      "views": 8
    }
  ],
  "lifetime": {
    "period": {
      "start": "2026-05-03",
      "end": "2026-07-12"
    },
    "totalPageviews": 16500,
    "countries": [
      {
        "code": "TW",
        "views": 5000
      },
      {
        "code": "CN",
        "views": 2000
      },
      {
        "code": "HK",
        "views": 1000
      },
      {
        "code": "US",
        "views": 1000
      },
      {
        "code": "VN",
        "views": 1000
      }
    ]
  }
}